Metadata-Version: 2.1
Name: nicrypt
Version: 0.0.3
Summary: A package for encrypting simple texts
Home-page: https://nkrtech.com
Author: Nicolus Rotich
Author-email: nicholas.rotich@gmail.com
License: MIT
Download-URL: https://github.com/moinonin/nicrypt/archive/refs/heads/main.zip
Project-URL: Bug Tracker, https://github.com/pypa/nicrypt/issues
Platform: any
Classifier: License :: OSI Approved :: MIT License
Requires-Python: >=3.7
License-File: LICENSE
